fic/__init__.py
fic/cli.py
fic/fic.py
fic-0.8.dist-info/entry_points.txt
fic-0.8.dist-info/LICENSE
fic-0.8.dist-info/WHEEL
fic-0.8.dist-info/METADATA
fic-0.8.dist-info/RECORD
