Metadata-Version: 2.1
Name: fic
Version: 0.8
Summary: Fast Image Compression
Author-email: Alyetama <56323389+Alyetama@users.noreply.github.com>
Classifier: License :: OSI Approved :: MIT License
Requires-Dist: tqdm
Requires-Dist: Pillow
Project-URL: Home, https://github.com/Alyetama/fast-image-compression
